{
    "needsErrorInfo": false,
    "boxShadow": "none",
    "mobileBottomRow": 10,
    "widgetName": "IconButton1",
    "buttonColor": "{{appsmith.theme.colors.primaryColor}}",
    "displayName": "Icon button",
    "iconSVG": "https://appcdn.appsmith.com/static/media/icon.bb5d55ae67fb1687dff78e66ad1faec0.svg",
    "searchTags": [
        "click",
        "submit"
    ],
    "topRow": 2,
    "bottomRow": 10,
    "type": "ICON_BUTTON_WIDGET",
    "hideCard": false,
    "mobileRightColumn": 62,
    "animateLoading": true,
    "dynamicTriggerPathList": [],
    "leftColumn": 48,
    "dynamicBindingPathList": [
        {"key": "buttonColor"},
        {"key": "borderRadius"}
    ],
    "isDisabled": false,
    "key": "p121ytkgtb",
    "isDeprecated": false,
    "rightColumn": 64,
    "thumbnailSVG": "https://appcdn.appsmith.com/static/media/thumbnail.b02b764a52db45d332efa723178a50a4.svg",
    "iconName": "dollar",
    "widgetId": "zrmp8hul6h",
    "buttonStyle": "PRIMARY",
    "minWidth": 50,
    "isVisible": true,
    "version": 1,
    "parentId": "ulv9g4tv4c",
    "tags": ["Buttons"],
    "renderMode": "CANVAS",
    "isLoading": false,
    "mobileTopRow": 2,
    "responsiveBehavior": "hug",
    "borderRadius": "{{appsmith.theme.borderRadius.appBorderRadius}}",
    "mobileLeftColumn": 46,
    "buttonVariant": "SECONDARY"
}