{
    "needsErrorInfo": false,
    "boxShadow": "none",
    "mobileBottomRow": 7,
    "widgetName": "IconButton1",
    "onClick": "{{showModal('Modal2');}}",
    "buttonColor": "{{appsmith.theme.colors.primaryColor}}",
    "displayName": "Icon button",
    "iconSVG": "https://appcdn.appsmith.com/static/media/icon.bb5d55ae67fb1687dff78e66ad1faec0.svg",
    "searchTags": [
        "click",
        "submit"
    ],
    "topRow": 1,
    "bottomRow": 8,
    "parentRowSpace": 10,
    "type": "ICON_BUTTON_WIDGET",
    "hideCard": false,
    "mobileRightColumn": 9,
    "animateLoading": true,
    "parentColumnSpace": 7.6904296875,
    "dynamicTriggerPathList": [{"key": "onClick"}],
    "leftColumn": 1,
    "dynamicBindingPathList": [
        {"key": "buttonColor"},
        {"key": "borderRadius"}
    ],
    "isDisabled": false,
    "key": "sxhgnkuu8w",
    "isDeprecated": false,
    "rightColumn": 13,
    "thumbnailSVG": "https://appcdn.appsmith.com/static/media/thumbnail.b02b764a52db45d332efa723178a50a4.svg",
    "iconName": "tick-circle",
    "dynamicHeight": "FIXED",
    "widgetId": "s71dvjkfk1",
    "minWidth": 50,
    "isVisible": true,
    "version": 1,
    "parentId": "n04zqee0rg",
    "tags": ["Buttons"],
    "renderMode": "CANVAS",
    "isLoading": false,
    "mobileTopRow": 3,
    "responsiveBehavior": "hug",
    "borderRadius": "{{appsmith.theme.borderRadius.appBorderRadius}}",
    "mobileLeftColumn": 5,
    "buttonVariant": "PRIMARY"
}