{
    "boxShadow": "{{appsmith.theme.boxShadow.appBoxShadow}}",
    "borderColor": "#E0DEDE",
    "isVisibleDownload": true,
    "iconSVG": "/static/media/icon.e6911f8bb94dc6c4a102a74740c41763.svg",
    "topRow": 68,
    "isSortable": true,
    "type": "TABLE_WIDGET_V2",
    "inlineEditingSaveOption": "ROW_LEVEL",
    "animateLoading": true,
    "dynamicBindingPathList": [
        {"key": "accentColor"},
        {"key": "borderRadius"},
        {"key": "boxShadow"},
        {"key": "tableData"},
        {"key": "primaryColumns.AccountID.computedValue"},
        {"key": "primaryColumns.Budget_id.computedValue"},
        {"key": "primaryColumns.CategoryID.computedValue"},
        {"key": "primaryColumns.MadeFor.computedValue"},
        {"key": "primaryColumns.MaxAmount.computedValue"},
        {"key": "primaryColumns.MinRemaining.computedValue"},
        {"key": "primaryColumns.Remaining.computedValue"},
        {"key": "primaryColumns.Spent.computedValue"}
    ],
    "needsHeightForContent": true,
    "leftColumn": 31,
    "delimiter": ",",
    "defaultSelectedRowIndex": 0,
    "flexVerticalAlignment": "start",
    "accentColor": "{{appsmith.theme.colors.primaryColor}}",
    "isVisibleFilters": true,
    "isVisible": false,
    "enableClientSideSearch": true,
    "version": 2,
    "totalRecordsCount": 0,
    "tags": [
        "Suggested",
        "Display"
    ],
    "isLoading": false,
    "childStylesheet": {
        "button": {
            "boxShadow": "none",
            "borderRadius": "{{appsmith.theme.borderRadius.appBorderRadius}}",
            "buttonColor": "{{appsmith.theme.colors.primaryColor}}"
        },
        "iconButton": {
            "boxShadow": "none",
            "borderRadius": "{{appsmith.theme.borderRadius.appBorderRadius}}",
            "buttonColor": "{{appsmith.theme.colors.primaryColor}}"
        },
        "menuButton": {
            "boxShadow": "none",
            "borderRadius": "{{appsmith.theme.borderRadius.appBorderRadius}}",
            "menuColor": "{{appsmith.theme.colors.primaryColor}}"
        },
        "editActions": {
            "saveButtonColor": "{{appsmith.theme.colors.primaryColor}}",
            "saveBorderRadius": "{{appsmith.theme.borderRadius.appBorderRadius}}",
            "discardBorderRadius": "{{appsmith.theme.borderRadius.appBorderRadius}}",
            "discardButtonColor": "{{appsmith.theme.colors.primaryColor}}"
        }
    },
    "borderRadius": "{{appsmith.theme.borderRadius.appBorderRadius}}",
    "columnUpdatedAt": 1713379831303,
    "originalBottomRow": 96,
    "defaultSelectedRowIndices": [0],
    "needsErrorInfo": false,
    "mobileBottomRow": 79,
    "widgetName": "Table1",
    "defaultPageSize": 0,
    "columnOrder": [
        "AccountID",
        "Budget_id",
        "CategoryID",
        "MadeFor",
        "MaxAmount",
        "MinRemaining",
        "Remaining",
        "Spent"
    ],
    "dynamicPropertyPathList": [{"key": "tableData"}],
    "displayName": "Table",
    "bottomRow": 96,
    "columnWidthMap": {},
    "parentRowSpace": 10,
    "hideCard": false,
    "mobileRightColumn": 53,
    "parentColumnSpace": 17.9375,
    "dynamicTriggerPathList": [],
    "borderWidth": "1",
    "primaryColumns": {
        "Budget_id": {
            "computedValue": "{{Table1.processedTableData.map((currentRow, currentIndex) => ( currentRow[\"Budget_id\"]))}}",
            "isEditable": false,
            "notation": "standard",
            "alias": "Budget_id",
            "enableSort": true,
            "isSaveVisible": true,
            "id": "Budget_id",
            "isDisabled": false,
            "allowSameOptionsInNewRow": true,
            "validation": {},
            "isCellVisible": true,
            "isDerived": false,
            "textSize": "0.875rem",
            "allowCellWrapping": false,
            "index": 1,
            "isDiscardVisible": true,
            "isVisible": true,
            "label": "Budget_id",
            "columnType": "number",
            "thousandSeparator": true,
            "horizontalAlignment": "LEFT",
            "isCellEditable": false,
            "decimals": 0,
            "width": 150,
            "enableFilter": true,
            "sticky": "",
            "originalId": "Budget_id",
            "currencyCode": "USD",
            "verticalAlignment": "CENTER"
        },
        "CategoryID": {
            "computedValue": "{{Table1.processedTableData.map((currentRow, currentIndex) => ( currentRow[\"CategoryID\"]))}}",
            "isEditable": false,
            "notation": "standard",
            "alias": "CategoryID",
            "enableSort": true,
            "isSaveVisible": true,
            "id": "CategoryID",
            "isDisabled": false,
            "allowSameOptionsInNewRow": true,
            "validation": {},
            "isCellVisible": true,
            "isDerived": false,
            "textSize": "0.875rem",
            "allowCellWrapping": false,
            "index": 2,
            "isDiscardVisible": true,
            "isVisible": true,
            "label": "CategoryID",
            "columnType": "number",
            "thousandSeparator": true,
            "horizontalAlignment": "LEFT",
            "isCellEditable": false,
            "decimals": 0,
            "width": 150,
            "enableFilter": true,
            "sticky": "",
            "originalId": "CategoryID",
            "currencyCode": "USD",
            "verticalAlignment": "CENTER"
        },
        "MinRemaining": {
            "computedValue": "{{Table1.processedTableData.map((currentRow, currentIndex) => ( currentRow[\"MinRemaining\"]))}}",
            "isEditable": false,
            "notation": "standard",
            "alias": "MinRemaining",
            "enableSort": true,
            "isSaveVisible": true,
            "id": "MinRemaining",
            "isDisabled": false,
            "allowSameOptionsInNewRow": true,
            "validation": {},
            "isCellVisible": true,
            "isDerived": false,
            "textSize": "0.875rem",
            "allowCellWrapping": false,
            "index": 5,
            "isDiscardVisible": true,
            "isVisible": true,
            "label": "MinRemaining",
            "columnType": "number",
            "thousandSeparator": true,
            "horizontalAlignment": "LEFT",
            "isCellEditable": false,
            "decimals": 0,
            "width": 150,
            "enableFilter": true,
            "sticky": "",
            "originalId": "MinRemaining",
            "currencyCode": "USD",
            "verticalAlignment": "CENTER"
        },
        "MadeFor": {
            "computedValue": "{{Table1.processedTableData.map((currentRow, currentIndex) => ( currentRow[\"MadeFor\"]))}}",
            "isEditable": false,
            "notation": "standard",
            "alias": "MadeFor",
            "enableSort": true,
            "isSaveVisible": true,
            "id": "MadeFor",
            "isDisabled": false,
            "allowSameOptionsInNewRow": true,
            "validation": {},
            "isCellVisible": true,
            "isDerived": false,
            "textSize": "0.875rem",
            "allowCellWrapping": false,
            "index": 3,
            "isDiscardVisible": true,
            "isVisible": true,
            "label": "MadeFor",
            "columnType": "text",
            "thousandSeparator": true,
            "horizontalAlignment": "LEFT",
            "isCellEditable": false,
            "decimals": 0,
            "width": 150,
            "enableFilter": true,
            "sticky": "",
            "originalId": "MadeFor",
            "currencyCode": "USD",
            "verticalAlignment": "CENTER"
        },
        "AccountID": {
            "computedValue": "{{Table1.processedTableData.map((currentRow, currentIndex) => ( currentRow[\"AccountID\"]))}}",
            "isEditable": false,
            "notation": "standard",
            "alias": "AccountID",
            "enableSort": true,
            "isSaveVisible": true,
            "id": "AccountID",
            "isDisabled": false,
            "allowSameOptionsInNewRow": true,
            "validation": {},
            "isCellVisible": true,
            "isDerived": false,
            "textSize": "0.875rem",
            "allowCellWrapping": false,
            "index": 0,
            "isDiscardVisible": true,
            "isVisible": true,
            "label": "AccountID",
            "columnType": "number",
            "thousandSeparator": true,
            "horizontalAlignment": "LEFT",
            "isCellEditable": false,
            "decimals": 0,
            "width": 150,
            "enableFilter": true,
            "sticky": "",
            "originalId": "AccountID",
            "currencyCode": "USD",
            "verticalAlignment": "CENTER"
        },
        "Spent": {
            "computedValue": "{{Table1.processedTableData.map((currentRow, currentIndex) => ( currentRow[\"Spent\"]))}}",
            "isEditable": false,
            "notation": "standard",
            "alias": "Spent",
            "enableSort": true,
            "isSaveVisible": true,
            "id": "Spent",
            "isDisabled": false,
            "allowSameOptionsInNewRow": true,
            "validation": {},
            "isCellVisible": true,
            "isDerived": false,
            "textSize": "0.875rem",
            "allowCellWrapping": false,
            "index": 7,
            "isDiscardVisible": true,
            "isVisible": true,
            "label": "Spent",
            "columnType": "number",
            "thousandSeparator": true,
            "horizontalAlignment": "LEFT",
            "isCellEditable": false,
            "decimals": 0,
            "width": 150,
            "enableFilter": true,
            "sticky": "",
            "originalId": "Spent",
            "currencyCode": "USD",
            "verticalAlignment": "CENTER"
        },
        "Remaining": {
            "computedValue": "{{Table1.processedTableData.map((currentRow, currentIndex) => ( currentRow[\"Remaining\"]))}}",
            "isEditable": false,
            "notation": "standard",
            "alias": "Remaining",
            "enableSort": true,
            "isSaveVisible": true,
            "id": "Remaining",
            "isDisabled": false,
            "allowSameOptionsInNewRow": true,
            "validation": {},
            "isCellVisible": true,
            "isDerived": false,
            "textSize": "0.875rem",
            "allowCellWrapping": false,
            "index": 6,
            "isDiscardVisible": true,
            "isVisible": true,
            "label": "Remaining",
            "columnType": "number",
            "thousandSeparator": true,
            "horizontalAlignment": "LEFT",
            "isCellEditable": false,
            "decimals": 0,
            "width": 150,
            "enableFilter": true,
            "sticky": "",
            "originalId": "Remaining",
            "currencyCode": "USD",
            "verticalAlignment": "CENTER"
        },
        "MaxAmount": {
            "computedValue": "{{Table1.processedTableData.map((currentRow, currentIndex) => ( currentRow[\"MaxAmount\"]))}}",
            "isEditable": false,
            "notation": "standard",
            "alias": "MaxAmount",
            "enableSort": true,
            "isSaveVisible": true,
            "id": "MaxAmount",
            "isDisabled": false,
            "allowSameOptionsInNewRow": true,
            "validation": {},
            "isCellVisible": true,
            "isDerived": false,
            "textSize": "0.875rem",
            "allowCellWrapping": false,
            "index": 4,
            "isDiscardVisible": true,
            "isVisible": true,
            "label": "MaxAmount",
            "columnType": "number",
            "thousandSeparator": true,
            "horizontalAlignment": "LEFT",
            "isCellEditable": false,
            "decimals": 0,
            "width": 150,
            "enableFilter": true,
            "sticky": "",
            "originalId": "MaxAmount",
            "currencyCode": "USD",
            "verticalAlignment": "CENTER"
        }
    },
    "key": "q035hxe5w1",
    "canFreezeColumn": true,
    "isDeprecated": false,
    "rightColumn": 64,
    "textSize": "0.875rem",
    "widgetId": "vzy2qlyzhu",
    "minWidth": 450,
    "tableData": "{{get_budgets_accountID.data}}",
    "label": "Data",
    "searchKey": "",
    "parentId": "0",
    "renderMode": "CANVAS",
    "mobileTopRow": 51,
    "horizontalAlignment": "LEFT",
    "isVisibleSearch": true,
    "responsiveBehavior": "fill",
    "originalTopRow": 68,
    "mobileLeftColumn": 19,
    "isVisiblePagination": true,
    "verticalAlignment": "CENTER"
}